[
  {
    "phoneNumber": "972537132140",
    "dayRequested": "מעולה!\nרשמנו שתרצה שניצור איתך קשר ביום חמישי בין השעות [12:00-15:00].\nנחזור אליך בתיאום הזה. תודה רבה על זמנך!"
  },
  {
    "phoneNumber": "972542086830",
    "dayRequested": "מעולה!\nרשמנו שתרצה שניצור איתך קשר ביום חמישי בין השעות [12:00-15:00].\nנחזור אליך בתיאום הזה. תודה רבה על זמנך!"
  },
  {
    "phoneNumber": "972542086830",
    "dayRequested": "מעולה!\nרשמנו שתרצה שניצור איתך קשר ביום חמישי בין השעות [15:00-18:00].\nנחזור אליך בתיאום הזה. תודה רבה על זמנך!"
  }
]